z3c.recipe.tag-1.0-py3.10-nspkg.pth
z3c/recipe/tag/__init__.py
z3c/recipe/tag/id-lang.map.txt
z3c/recipe/tag/tests.py
z3c.recipe.tag-1.0.dist-info/LICENSE.rst
z3c.recipe.tag-1.0.dist-info/METADATA
z3c.recipe.tag-1.0.dist-info/WHEEL
z3c.recipe.tag-1.0.dist-info/entry_points.txt
z3c.recipe.tag-1.0.dist-info/namespace_packages.txt
z3c.recipe.tag-1.0.dist-info/top_level.txt
z3c.recipe.tag-1.0.dist-info/RECORD
