Metadata-Version: 2.1
Name: z3c.recipe.tag
Version: 1.0
Summary: Generate ctags from eggs for development.
Home-page: https://github.com/zopefoundation/z3c.recipe.tag
Author: Ignas Mikalajūnas and the Zope Community
Maintainer: Paul Carduner
Maintainer-email: zope-dev@zope.dev
License: ZPL 2.1
Classifier: Development Status :: 5 - Production/Stable
Classifier: Intended Audience :: Developers
Classifier: License :: OSI Approved :: Zope Public License
Classifier: Operating System :: OS Independent
Classifier: Programming Language :: Python
Classifier: Programming Language :: Python :: 3.7
Classifier: Programming Language :: Python :: 3.8
Classifier: Programming Language :: Python :: 3.9
Classifier: Programming Language :: Python :: 3.10
Classifier: Programming Language :: Python :: 3.11
Classifier: Programming Language :: Python :: Implementation :: CPython
Classifier: Programming Language :: Python :: Implementation :: PyPy
Classifier: Framework :: Buildout
Classifier: Topic :: Software Development :: Build Tools
Classifier: Topic :: Text Editors :: Emacs
Classifier: Topic :: Utilities
Requires-Python: >=3.7
License-File: LICENSE.rst
Requires-Dist: setuptools
Requires-Dist: zc.buildout (>=3.0)
Requires-Dist: zc.recipe.egg
Provides-Extra: test
Requires-Dist: zope.testing ; extra == 'test'
Requires-Dist: zope.testrunner ; extra == 'test'
